Astras/Agniastra.py
Astras/Brahmastra.py
Astras/__init__.py
Astras-0.2.dist-info/LICENSE
Astras-0.2.dist-info/METADATA
Astras-0.2.dist-info/WHEEL
Astras-0.2.dist-info/top_level.txt
Astras-0.2.dist-info/RECORD
