Metadata-Version: 2.1
Name: Astras
Version: 0.2
Summary: Package for Classification and Regression
Home-page: https://github.com/Harsh502s/Astras
Author: Harshit Singh
Author-email: harsh502singh@gmail.com
License: UNKNOWN
Platform: UNKNOWN
Classifier: Programming Language :: Python :: 3
Classifier: License :: OSI Approved :: MIT License
Classifier: Operating System :: OS Independent
Requires-Python: >=3.6
License-File: LICENSE
Requires-Dist: pandas
Requires-Dist: numpy
Requires-Dist: matplotlib
Requires-Dist: seaborn
Requires-Dist: scikit-learn
Requires-Dist: xgboost
Requires-Dist: catboost
